{"viewport_width":536,"camera_move_speed":0.3,"map_pos":{"42177bd3-5e60-4b2f-b56a-60231b052e2e":{"z":30,"y":68,"x":30},"960c6ae5-9aab-4d01-9a69-4da658636e4d":{"z":30,"y":68,"x":30},"map4":{"z":30,"y":68,"x":30},"7e5ddfc0-867a-435f-ab4d-9a5a1018f622":{"z":30,"y":68,"x":30},"map3":{"z":30,"y":68,"x":30},"87884dad-67c4-40c9-bbaa-d12537f05656":{"z":30,"y":68,"x":30},"map2":{"z":30,"y":68,"x":30},"map001":{"z":30,"y":68,"x":30}},"part_place_settings":[{"color":{"g":255,"__OBJ_TYPE":"Color","r":255,"a":255,"b":255},"__OBJ_TYPE":"PART_PLACE_SETTING","texture":"part_mutou.tga","key":"cube"},{"color":{"g":255,"__OBJ_TYPE":"Color","r":255,"a":255,"b":255},"__OBJ_TYPE":"PART_PLACE_SETTING","texture":"part_suliao.tga","key":"sphere"},{"color":{"g":255,"__OBJ_TYPE":"Color","r":255,"a":255,"b":255},"__OBJ_TYPE":"PART_PLACE_SETTING","texture":"part_suliao.tga","key":"cylinder"},{"color":{"g":255,"__OBJ_TYPE":"Color","r":255,"a":255,"b":255},"__OBJ_TYPE":"PART_PLACE_SETTING","texture":"part_suliao.tga","key":"cone"}],"viewport_height":301}